fyta_cli/__init__.py
fyta_cli/fyta_client.py
fyta_cli/fyta_connector.py
fyta_cli/fyta_exceptions.py
fyta_cli/fyta_models.py
fyta_cli/py.typed
fyta_cli-0.7.2.dist-info/METADATA
fyta_cli-0.7.2.dist-info/WHEEL
fyta_cli-0.7.2.dist-info/licenses/LICENSE
fyta_cli-0.7.2.dist-info/RECORD
